{
    "features": [
        {
            "geometry": {
                "coordinates": [
                    -0.190889,
                    51.5807555
                ],
                "type": "Point"
            },
            "properties": {
                "description": "Grade I listed Non-conformist church, set in the suburb's integrally planned Central Square to balance St Jude's Church nearby, but with a low concrete dome. Distinctive interior with large Tuscan columns on high brick plinths.",
                "end": "16:00:00",
                "fully_booked": "",
                "name": "Hampstead Garden Suburb Free Church",
                "start": "14:00:00",
                "ticketed_events": "No",
                "url": "https://programme.openhouse.org.uk/listings/2297"
            },
            "type": "Feature"
        }
    ],
    "type": "FeatureCollection"
}