{
    "features": [
        {
            "geometry": {
                "coordinates": [
                    -0.10871,
                    51.52336
                ],
                "type": "Point"
            },
            "properties": {
                "balloted": "No",
                "description": "Bringing together placemakers from across England. Join us for an online event series led by our Associates and discover the questions, challenges, and inspirations at the forefront of their minds after one year of working in local gov.",
                "end": "14:00:00",
                "fully_booked": "No",
                "images": [
                    {
                        "archive_url": "https://raw.githubusercontent.com/Jonty/open-house-london-images/master/images/2023/12246/building_12246_a22_talks_eventbrite-collection-banner_associates_81f6e7503f1261fdf230cc072a8e016c.jpg",
                        "title": "Public Practice Associates from the Autumn 2022 Cohort"
                    },
                    {
                        "archive_url": "https://raw.githubusercontent.com/Jonty/open-house-london-images/master/images/2023/12246/building_12246_a22_talks_eventbrite_g1_v2_b5777949ceb5fc075b1b8071b537ba96.jpg",
                        "title": "Talk 1: Fair Exchange: Principles for Collaborative Placemaking"
                    },
                    {
                        "archive_url": "https://raw.githubusercontent.com/Jonty/open-house-london-images/master/images/2023/12246/building_12246_a22_talks_eventbrite_g2_v2_9fdb48376d2b565fead6311665891c0e.jpg",
                        "title": "Talk 2: Agility in a 'Rigid' Planning System"
                    },
                    {
                        "archive_url": "https://raw.githubusercontent.com/Jonty/open-house-london-images/master/images/2023/12246/building_12246_a22_talks_eventbrite_g3_v2_ad96397ca52ea9d123d036542b03b82c.jpg",
                        "title": "Talk 3: Climate Change: Transferable Actions for Local Authorities"
                    },
                    {
                        "archive_url": "https://raw.githubusercontent.com/Jonty/open-house-london-images/master/images/2023/12246/building_12246_a22_talks_eventbrite_g4_d8dfbbc4740b5ee966419e6ea9fb5ba3.jpg",
                        "title": "Talk 4: What is local government's role in Pride in Place?"
                    }
                ],
                "name": "Public Practice Talks (Online Only)",
                "new_venue_this_year": "Yes",
                "start": "13:00:00",
                "ticketed_events": "Yes",
                "url": "https://programme.openhouse.org.uk/listings/12246"
            },
            "type": "Feature"
        }
    ],
    "type": "FeatureCollection"
}