{
    "features": [
        {
            "geometry": {
                "coordinates": [
                    -0.1340543,
                    51.5126804
                ],
                "type": "Point"
            },
            "properties": {
                "description": "SODA Studio will lead two tours of Soho by day and by night to explore both historic and contemporary buildings that they know and love, which help create the modern 'village' we know today.",
                "end": "12:00:00",
                "fully_booked": "Yes",
                "name": "Soho tour by SODA Studio",
                "start": "11:00:00",
                "ticketed_events": "Yes",
                "url": "https://openhouselondon.open-city.org.uk/listings/9210"
            },
            "type": "Feature"
        },
        {
            "geometry": {
                "coordinates": [
                    -0.2987655,
                    51.4856009
                ],
                "type": "Point"
            },
            "properties": {
                "description": "Studio Flox at Watermans Art Centre is a combined arts centre. It is located in Brentford, England alongside the banks of the River Thames overlooking Kew Gardens in West London, England",
                "end": "16:00:00",
                "fully_booked": "",
                "name": "Studio Flox",
                "start": "08:00:00",
                "ticketed_events": "No",
                "url": "https://openhouselondon.open-city.org.uk/listings/10281"
            },
            "type": "Feature"
        }
    ],
    "type": "FeatureCollection"
}