{
    "features": [
        {
            "geometry": {
                "coordinates": [
                    -0.12543,
                    51.5366379
                ],
                "type": "Point"
            },
            "properties": {
                "balloted": "No",
                "description": "The Stirling-prize shortlisted King’s Cross Masterplan established a framework for the incremental redevelopment of this industrial heritage site through a mix of uses and a network of public spaces structuring new urban blocks and knitting the site into its context.",
                "end": "15:00:00",
                "fully_booked": "Yes",
                "images": [
                    {
                        "archive_url": "https://raw.githubusercontent.com/infrastructureclub/open-house-london-images/master/images/2025/7788/building_7788_aam_kx_granarysquare1_4964e1eef80f2fc5f37931ca762203cc.jpg",
                        "title": "Granary Square at King's Cross. Courtesy of John Sturrock and Related Argent"
                    },
                    {
                        "archive_url": "https://raw.githubusercontent.com/infrastructureclub/open-house-london-images/master/images/2025/7788/building_7788_kxc_image-1_174beaa5c8acfb2136ed8b00e9940cd1.jpg",
                        "title": ""
                    },
                    {
                        "archive_url": "https://raw.githubusercontent.com/infrastructureclub/open-house-london-images/master/images/2025/7788/building_7788_kxc_image-2_0f16759b4f8bf6d4f85fe2468ad50f48.jpg",
                        "title": ""
                    },
                    {
                        "archive_url": "https://raw.githubusercontent.com/infrastructureclub/open-house-london-images/master/images/2025/7788/building_7788_kxc_image-3_cf5bb1a2fc971f27056eebd390c41805.jpg",
                        "title": ""
                    },
                    {
                        "archive_url": "https://raw.githubusercontent.com/infrastructureclub/open-house-london-images/master/images/2025/7788/building_7788_kxc_image-4_9ae23b8f753a5043aea55c08fb715838.jpg",
                        "title": ""
                    },
                    {
                        "archive_url": "https://raw.githubusercontent.com/infrastructureclub/open-house-london-images/master/images/2025/7788/building_7788_kxc_image-5_b2e0c6043bb9d5f3a0647bdc30ee9167.jpg",
                        "title": ""
                    },
                    {
                        "archive_url": "https://raw.githubusercontent.com/infrastructureclub/open-house-london-images/master/images/2025/7788/building_7788_kxc_image-6_247bfec58a539b918b54c6ed6ac5b6d7.jpg",
                        "title": ""
                    },
                    {
                        "archive_url": "https://raw.githubusercontent.com/infrastructureclub/open-house-london-images/master/images/2025/7788/building_7788_kxc_image-7_ba9fb0ca723300004b2a74581f6349d1.jpg",
                        "title": ""
                    },
                    {
                        "archive_url": "https://raw.githubusercontent.com/infrastructureclub/open-house-london-images/master/images/2025/7788/building_7788_kxc_image-8_84262d1b5d1f1b13c8b039a4601239fb.jpg",
                        "title": ""
                    },
                    {
                        "archive_url": "https://raw.githubusercontent.com/infrastructureclub/open-house-london-images/master/images/2025/7788/building_7788_aam_kx_bagleywalk_24327f1c591e95a4505a9ef3ac9e77d1.jpg",
                        "title": "Bagley Walk at King's Cross. Courtesy of John Sturrock and Related Argent"
                    }
                ],
                "name": "King's Cross Masterplan",
                "new_venue_this_year": "No",
                "start": "13:00:00",
                "ticketed_events": "Yes",
                "url": "https://programme.openhouse.org.uk/listings/7788"
            },
            "type": "Feature"
        }
    ],
    "type": "FeatureCollection"
}